pibs/__init__.py
pibs/propagate.py
pibs/setup.py
pibs/util.py
pibs-0.1.0.dist-info/METADATA
pibs-0.1.0.dist-info/WHEEL
pibs-0.1.0.dist-info/licenses/LICENSE
pibs-0.1.0.dist-info/RECORD
