Metadata-Version: 2.4
Name: pibs
Version: 0.1.0
Summary: PIBS: Permutational Invariance Block Solver implements a numerically exact method for solving the dissipative Tavis-Cummings model with local losses
Project-URL: Homepage, https://github.com/lukasfreter/pibs/tree/main
Author-email: Lukas Freter <lukas.freter@aalto.fi>, Piper Fowler-Wright <piperfw@gmail.com>
License-Expression: GPL-3.0-or-later
License-File: LICENSE
Keywords: cavity-qed,computational-physics,open-quantum-system,physics,superradiance
Classifier: License :: OSI Approved :: GNU General Public License v3 or later (GPLv3+)
Classifier: Programming Language :: Python
Classifier: Topic :: Scientific/Engineering :: Physics
Requires-Python: <3.14,>=3.10
Requires-Dist: numpy
Requires-Dist: scipy
